actable/__init__.py
actable/apps.py
actable/helpers.py
actable/models.py
actable/signals.py
actable/urls.py
actable/utils.py
actable/views.py
actable/migrations/0001_initial.py
actable/migrations/__init__.py
actable/static/css/actable.css
actable/static/js/actable.js
actable-0.1.2.dist-info/DESCRIPTION.rst
actable-0.1.2.dist-info/METADATA
actable-0.1.2.dist-info/RECORD
actable-0.1.2.dist-info/WHEEL
actable-0.1.2.dist-info/metadata.json
actable-0.1.2.dist-info/top_level.txt
