Metadata-Version: 2.0
Name: actable
Version: 0.1.2
Summary: Flexible activity stream supporting multiple associated objects and fast denormalized look-ups
Home-page: https://github.com/michaelpb/actable
Author: michaelb
Author-email: michaelpb@gmail.com
License: Apache Software License 2.0
Keywords: actable
Platform: UNKNOWN
Classifier: Development Status :: 3 - Alpha
Classifier: Framework :: Django
Classifier: Framework :: Django :: 1.8
Classifier: Framework :: Django :: 1.9
Classifier: Framework :: Django :: 1.10
Classifier: Intended Audience :: Developers
Classifier: License :: OSI Approved :: BSD License
Classifier: Natural Language :: English
Classifier: Programming Language :: Python :: 2
Classifier: Programming Language :: Python :: 2.7
Classifier: Programming Language :: Python :: 3
Classifier: Programming Language :: Python :: 3.3
Classifier: Programming Language :: Python :: 3.4
Classifier: Programming Language :: Python :: 3.5
